{
    "meta": {
        "last_update": "2026-04-06 09:07:32",
        "source": "BarajMetre (Mega Paket - Hibrit)"
    },
    "cities": [
        {
            "city": "İstanbul",
            "rate": 36.5,
            "status": "success",
            "last_check": "2026-04-06T09:04:59.325886"
        },
        {
            "city": "Ankara",
            "rate": 36.68,
            "status": "success",
            "last_check": "2026-04-06T09:05:00.528861"
        },
        {
            "city": "Bursa",
            "rate": 95.61,
            "status": "success",
            "last_check": "2026-04-06T09:05:04.804169"
        },
        {
            "city": "Adana",
            "rate": 95.56,
            "status": "success",
            "last_check": "2026-04-06T09:05:11.805649"
        },
        {
            "city": "Trabzon",
            "rate": 100.0,
            "status": "success",
            "last_check": "2026-04-06T09:05:16.849786"
        },
        {
            "city": "Aydın",
            "rate": 69.05,
            "status": "success",
            "last_check": "2026-04-06T09:05:20.764164"
        },
        {
            "city": "Balıkesir",
            "rate": 95.68,
            "status": "success",
            "last_check": "2026-04-06T09:06:50.768165"
        },
        {
            "city": "Muğla",
            "rate": 92.0,
            "status": "success",
            "last_check": "2026-04-06T09:06:57.708873"
        },
        {
            "city": "Sakarya",
            "rate": 29.39,
            "status": "success",
            "last_check": "2026-04-06T09:07:05.356576"
        },
        {
            "city": "Erzurum",
            "rate": 35.0,
            "status": "success",
            "last_check": "2026-04-06T09:07:05.356598"
        },
        {
            "city": "İzmir",
            "rate": 53.62,
            "status": "success",
            "last_check": "2026-04-06T09:07:06.936411"
        },
        {
            "city": "Kocaeli",
            "rate": 91.1,
            "status": "success",
            "last_check": "2026-04-06T09:07:13.100721"
        },
        {
            "city": "Samsun",
            "rate": 96.75,
            "status": "success",
            "last_check": "2026-04-06T09:07:28.088192"
        },
        {
            "city": "Konya",
            "rate": 17.13,
            "status": "success",
            "last_check": "2026-04-06T09:07:32.887362"
        },
        {
            "city": "Edirne",
            "rate": 55.4,
            "status": "manual",
            "last_check": "2026-04-06T09:07:32.930358"
        },
        {
            "city": "Tekirdağ",
            "rate": 42.1,
            "status": "manual",
            "last_check": "2026-04-06T09:07:32.930372"
        },
        {
            "city": "Çanakkale",
            "rate": 38.5,
            "status": "manual",
            "last_check": "2026-04-06T09:07:32.930376"
        },
        {
            "city": "Manisa",
            "rate": 25.0,
            "status": "manual",
            "last_check": "2026-04-06T09:07:32.930379"
        },
        {
            "city": "Antalya",
            "rate": 48.75,
            "status": "manual",
            "last_check": "2026-04-06T09:07:32.930383"
        },
        {
            "city": "Mersin",
            "rate": 60.2,
            "status": "manual",
            "last_check": "2026-04-06T09:07:32.930386"
        },
        {
            "city": "Hatay",
            "rate": 35.0,
            "status": "manual",
            "last_check": "2026-04-06T09:07:32.930389"
        },
        {
            "city": "Gaziantep",
            "rate": 20.15,
            "status": "manual",
            "last_check": "2026-04-06T09:07:32.930392"
        },
        {
            "city": "Kahramanmaraş",
            "rate": 45.0,
            "status": "manual",
            "last_check": "2026-04-06T09:07:32.930396"
        },
        {
            "city": "Malatya",
            "rate": 45.5,
            "status": "manual",
            "last_check": "2026-04-06T09:07:32.930398"
        },
        {
            "city": "Sivas",
            "rate": 22.8,
            "status": "manual",
            "last_check": "2026-04-06T09:07:32.930402"
        },
        {
            "city": "Kayseri",
            "rate": 30.0,
            "status": "manual",
            "last_check": "2026-04-06T09:07:32.930405"
        },
        {
            "city": "Eskişehir",
            "rate": 40.0,
            "status": "manual",
            "last_check": "2026-04-06T09:07:32.930408"
        },
        {
            "city": "Kütahya",
            "rate": 50.0,
            "status": "manual",
            "last_check": "2026-04-06T09:07:32.930412"
        },
        {
            "city": "Yozgat",
            "rate": 15.0,
            "status": "manual",
            "last_check": "2026-04-06T09:07:32.930415"
        },
        {
            "city": "Çorum",
            "rate": 28.0,
            "status": "manual",
            "last_check": "2026-04-06T09:07:32.930418"
        },
        {
            "city": "Tokat",
            "rate": 33.0,
            "status": "manual",
            "last_check": "2026-04-06T09:07:32.930421"
        },
        {
            "city": "Amasya",
            "rate": 41.0,
            "status": "manual",
            "last_check": "2026-04-06T09:07:32.930425"
        },
        {
            "city": "Elazığ",
            "rate": 55.0,
            "status": "manual",
            "last_check": "2026-04-06T09:07:32.930428"
        },
        {
            "city": "Diyarbakır",
            "rate": 60.0,
            "status": "manual",
            "last_check": "2026-04-06T09:07:32.930432"
        },
        {
            "city": "Batman",
            "rate": 65.0,
            "status": "manual",
            "last_check": "2026-04-06T09:07:32.930435"
        },
        {
            "city": "Şanlıurfa",
            "rate": 70.0,
            "status": "manual",
            "last_check": "2026-04-06T09:07:32.930438"
        },
        {
            "city": "Mardin",
            "rate": 25.0,
            "status": "manual",
            "last_check": "2026-04-06T09:07:32.930442"
        },
        {
            "city": "Van",
            "rate": 35.0,
            "status": "manual",
            "last_check": "2026-04-06T09:07:32.930445"
        },
        {
            "city": "Kars",
            "rate": 40.0,
            "status": "manual",
            "last_check": "2026-04-06T09:07:32.930449"
        },
        {
            "city": "Denizli",
            "rate": 18.0,
            "status": "manual",
            "last_check": "2026-04-06T09:07:32.930452"
        }
    ]
}