{
    "meta": {
        "last_update": "2026-03-27 08:47:54",
        "source": "BarajMetre (Mega Paket - Hibrit)"
    },
    "cities": [
        {
            "city": "İstanbul",
            "rate": 36.5,
            "status": "success",
            "last_check": "2026-03-27T08:45:20.851623"
        },
        {
            "city": "Ankara",
            "rate": 29.88,
            "status": "success",
            "last_check": "2026-03-27T08:45:21.853969"
        },
        {
            "city": "Bursa",
            "rate": 75.35,
            "status": "success",
            "last_check": "2026-03-27T08:45:26.409981"
        },
        {
            "city": "Adana",
            "rate": 92.59,
            "status": "success",
            "last_check": "2026-03-27T08:45:33.198187"
        },
        {
            "city": "Trabzon",
            "rate": 100.0,
            "status": "success",
            "last_check": "2026-03-27T08:45:38.912461"
        },
        {
            "city": "Aydın",
            "rate": 66.95,
            "status": "success",
            "last_check": "2026-03-27T08:45:42.732573"
        },
        {
            "city": "Balıkesir",
            "rate": 95.68,
            "status": "success",
            "last_check": "2026-03-27T08:47:12.734414"
        },
        {
            "city": "Muğla",
            "rate": 92.0,
            "status": "success",
            "last_check": "2026-03-27T08:47:21.969960"
        },
        {
            "city": "Sakarya",
            "rate": 29.13,
            "status": "success",
            "last_check": "2026-03-27T08:47:29.621018"
        },
        {
            "city": "Erzurum",
            "rate": 35.0,
            "status": "success",
            "last_check": "2026-03-27T08:47:29.621042"
        },
        {
            "city": "İzmir",
            "rate": 65.76,
            "status": "success",
            "last_check": "2026-03-27T08:47:30.947631"
        },
        {
            "city": "Kocaeli",
            "rate": 83.32,
            "status": "success",
            "last_check": "2026-03-27T08:47:36.323044"
        },
        {
            "city": "Samsun",
            "rate": 94.33,
            "status": "success",
            "last_check": "2026-03-27T08:47:50.746246"
        },
        {
            "city": "Konya",
            "rate": 15.93,
            "status": "success",
            "last_check": "2026-03-27T08:47:54.817069"
        },
        {
            "city": "Edirne",
            "rate": 55.4,
            "status": "manual",
            "last_check": "2026-03-27T08:47:54.863197"
        },
        {
            "city": "Tekirdağ",
            "rate": 42.1,
            "status": "manual",
            "last_check": "2026-03-27T08:47:54.863210"
        },
        {
            "city": "Çanakkale",
            "rate": 38.5,
            "status": "manual",
            "last_check": "2026-03-27T08:47:54.863213"
        },
        {
            "city": "Manisa",
            "rate": 25.0,
            "status": "manual",
            "last_check": "2026-03-27T08:47:54.863217"
        },
        {
            "city": "Antalya",
            "rate": 48.75,
            "status": "manual",
            "last_check": "2026-03-27T08:47:54.863220"
        },
        {
            "city": "Mersin",
            "rate": 60.2,
            "status": "manual",
            "last_check": "2026-03-27T08:47:54.863223"
        },
        {
            "city": "Hatay",
            "rate": 35.0,
            "status": "manual",
            "last_check": "2026-03-27T08:47:54.863227"
        },
        {
            "city": "Gaziantep",
            "rate": 20.15,
            "status": "manual",
            "last_check": "2026-03-27T08:47:54.863230"
        },
        {
            "city": "Kahramanmaraş",
            "rate": 45.0,
            "status": "manual",
            "last_check": "2026-03-27T08:47:54.863233"
        },
        {
            "city": "Malatya",
            "rate": 45.5,
            "status": "manual",
            "last_check": "2026-03-27T08:47:54.863236"
        },
        {
            "city": "Sivas",
            "rate": 22.8,
            "status": "manual",
            "last_check": "2026-03-27T08:47:54.863239"
        },
        {
            "city": "Kayseri",
            "rate": 30.0,
            "status": "manual",
            "last_check": "2026-03-27T08:47:54.863243"
        },
        {
            "city": "Eskişehir",
            "rate": 40.0,
            "status": "manual",
            "last_check": "2026-03-27T08:47:54.863246"
        },
        {
            "city": "Kütahya",
            "rate": 50.0,
            "status": "manual",
            "last_check": "2026-03-27T08:47:54.863249"
        },
        {
            "city": "Yozgat",
            "rate": 15.0,
            "status": "manual",
            "last_check": "2026-03-27T08:47:54.863252"
        },
        {
            "city": "Çorum",
            "rate": 28.0,
            "status": "manual",
            "last_check": "2026-03-27T08:47:54.863256"
        },
        {
            "city": "Tokat",
            "rate": 33.0,
            "status": "manual",
            "last_check": "2026-03-27T08:47:54.863259"
        },
        {
            "city": "Amasya",
            "rate": 41.0,
            "status": "manual",
            "last_check": "2026-03-27T08:47:54.863262"
        },
        {
            "city": "Elazığ",
            "rate": 55.0,
            "status": "manual",
            "last_check": "2026-03-27T08:47:54.863266"
        },
        {
            "city": "Diyarbakır",
            "rate": 60.0,
            "status": "manual",
            "last_check": "2026-03-27T08:47:54.863269"
        },
        {
            "city": "Batman",
            "rate": 65.0,
            "status": "manual",
            "last_check": "2026-03-27T08:47:54.863273"
        },
        {
            "city": "Şanlıurfa",
            "rate": 70.0,
            "status": "manual",
            "last_check": "2026-03-27T08:47:54.863277"
        },
        {
            "city": "Mardin",
            "rate": 25.0,
            "status": "manual",
            "last_check": "2026-03-27T08:47:54.863280"
        },
        {
            "city": "Van",
            "rate": 35.0,
            "status": "manual",
            "last_check": "2026-03-27T08:47:54.863283"
        },
        {
            "city": "Kars",
            "rate": 40.0,
            "status": "manual",
            "last_check": "2026-03-27T08:47:54.863287"
        },
        {
            "city": "Denizli",
            "rate": 18.0,
            "status": "manual",
            "last_check": "2026-03-27T08:47:54.863290"
        }
    ]
}